{
	"configurations" : 
	[
		{
			"directories" : 
			[
				{
					"build" : ".",
					"jsonFile" : "directory-.-Debug-f5ebdc15457944623624.json",
					"minimumCMakeVersion" : 
					{
						"string" : "3.10"
					},
					"projectIndex" : 0,
					"source" : ".",
					"targetIndexes" : 
					[
						0,
						1,
						2
					]
				}
			],
			"name" : "Debug",
			"projects" : 
			[
				{
					"directoryIndexes" : 
					[
						0
					],
					"name" : "lua",
					"targetIndexes" : 
					[
						0,
						1,
						2
					]
				}
			],
			"targets" : 
			[
				{
					"directoryIndex" : 0,
					"id" : "lua::@6890427a1f51a3e7e1df",
					"jsonFile" : "target-lua-Debug-ffc15cb0adf3a22204af.json",
					"name" : "lua",
					"projectIndex" : 0
				},
				{
					"directoryIndex" : 0,
					"id" : "luac::@6890427a1f51a3e7e1df",
					"jsonFile" : "target-luac-Debug-5a1861dc3d2cf120fe63.json",
					"name" : "luac",
					"projectIndex" : 0
				},
				{
					"directoryIndex" : 0,
					"id" : "luacli::@6890427a1f51a3e7e1df",
					"jsonFile" : "target-luacli-Debug-ba9312c084be255116a8.json",
					"name" : "luacli",
					"projectIndex" : 0
				}
			]
		}
	],
	"kind" : "codemodel",
	"paths" : 
	{
		"build" : "/home/ycy/repo/lua-5.3.6/cmake-build-debug",
		"source" : "/home/ycy/repo/lua-5.3.6"
	},
	"version" : 
	{
		"major" : 2,
		"minor" : 6
	}
}
